jira_cursor/__init__.py
jira_cursor/automation_service.py
jira_cursor/cli.py
jira_cursor/code_generator.py
jira_cursor/config.py
jira_cursor/cursor_cloud_client.py
jira_cursor/jira_client.py
jira_cursor/py.typed
jira_cursor/ticket_assessor.py
jira_cursor-0.1.1.dist-info/METADATA
jira_cursor-0.1.1.dist-info/WHEEL
jira_cursor-0.1.1.dist-info/entry_points.txt
jira_cursor-0.1.1.dist-info/RECORD
