Metadata-Version: 2.4
Name: jira-cursor
Version: 0.1.1
Summary: Enable Jira tickets to Cursor Cloud Agent draft PR automations.
Author-email: Rohith Bilgi Sampgod <77735942+rohith-bs@users.noreply.github.com>
License: MIT
Keywords: automation,ci-cd,cursor,cursor-cloud,jira,jira-integration,pr,pull-request
Classifier: Development Status :: 4 - Beta
Classifier: Intended Audience :: Developers
Classifier: License :: OSI Approved :: MIT License
Classifier: Operating System :: OS Independent
Classifier: Programming Language :: Python :: 3
Classifier: Programming Language :: Python :: 3.9
Classifier: Programming Language :: Python :: 3.10
Classifier: Programming Language :: Python :: 3.11
Classifier: Programming Language :: Python :: 3.12
Classifier: Topic :: Office/Business
Classifier: Topic :: Software Development :: Libraries :: Python Modules
Classifier: Topic :: Software Development :: Version Control :: Git
Requires-Python: >=3.9
Requires-Dist: pydantic>=2.0.0
Requires-Dist: python-dotenv>=1.0.0
Requires-Dist: requests>=2.31.0
Provides-Extra: dev
Requires-Dist: mypy>=1.0.0; extra == 'dev'
Requires-Dist: pytest-cov>=4.0.0; extra == 'dev'
Requires-Dist: pytest>=7.0.0; extra == 'dev'
Requires-Dist: types-requests>=2.31.0; extra == 'dev'
